databricks/__init__.py
databricks/sql/__init__.py
databricks/sql/auth/__init__.py
databricks/sql/auth/auth.py
databricks/sql/auth/authenticators.py
databricks/sql/auth/endpoint.py
databricks/sql/auth/oauth.py
databricks/sql/auth/oauth_http_handler.py
databricks/sql/auth/retry.py
databricks/sql/auth/thrift_http_client.py
databricks/sql/client.py
databricks/sql/cloudfetch/download_manager.py
databricks/sql/cloudfetch/downloader.py
databricks/sql/exc.py
databricks/sql/experimental/__init__.py
databricks/sql/experimental/oauth_persistence.py
databricks/sql/parameters/__init__.py
databricks/sql/parameters/native.py
databricks/sql/parameters/py.typed
databricks/sql/py.typed
databricks/sql/thrift_api/TCLIService/TCLIService-remote
databricks/sql/thrift_api/TCLIService/TCLIService.py
databricks/sql/thrift_api/TCLIService/__init__.py
databricks/sql/thrift_api/TCLIService/constants.py
databricks/sql/thrift_api/TCLIService/ttypes.py
databricks/sql/thrift_api/__init__.py
databricks/sql/thrift_backend.py
databricks/sql/types.py
databricks/sql/utils.py
databricks_sql_connector_core-4.0.1.dist-info/METADATA
databricks_sql_connector_core-4.0.1.dist-info/WHEEL
databricks_sql_connector_core-4.0.1.dist-info/RECORD
